PyThermalAnalysis/__init__.py
PyThermalAnalysis/exergy.py
PyThermalAnalysis/thermodynamics.py
PyThermalAnalysis-0.1.0.dist-info/LICENSE
PyThermalAnalysis-0.1.0.dist-info/METADATA
PyThermalAnalysis-0.1.0.dist-info/WHEEL
PyThermalAnalysis-0.1.0.dist-info/top_level.txt
PyThermalAnalysis-0.1.0.dist-info/RECORD
