Metadata-Version: 2.1
Name: PyThermalAnalysis
Version: 0.1.0
Summary: A Python library for a basic exergy analysis in thermodynamic systems
Home-page: https://github.com/nirmalparmarphd/PyThermalAnalysis
Author: Nirmal Parmar
Author-email: nirmalparmarphd@gmail.com
Classifier: Programming Language :: Python :: 3
Classifier: License :: OSI Approved :: MIT License
Classifier: Operating System :: OS Independent
Requires-Python: >=3.6
License-File: LICENSE
Requires-Dist: pandas
Requires-Dist: numpy
